<mediaList>
  <media>
    <title>Walking in Madrid LIVE 🇪🇸 | Spring Atmosphere &amp;amp; Street Life</title>
    <thumb>https://img.youtube.com/vi/G4q5LrvXx5I/0.jpg</thumb>
    <type>youtube</type>
    <src>G4q5LrvXx5I</src>
  </media><media>
    <title>Paris LIVE 🇫🇷 Walking Tour | Champs-Élysées Street Walk</title>
    <thumb>https://img.youtube.com/vi/-f6MOQbHCVQ/0.jpg</thumb>
    <type>youtube</type>
    <src>-f6MOQbHCVQ</src>
  </media><media>
    <title>LIVE From Barcelona 🇪🇸 | Walking Through the City Streets</title>
    <thumb>https://img.youtube.com/vi/U-fL8LtTTTk/0.jpg</thumb>
    <type>youtube</type>
    <src>U-fL8LtTTTk</src>
  </media><media>
    <title>London walk: London Street Walk 24/7 live stream | London Walking Tour</title>
    <thumb>https://img.youtube.com/vi/WKGK_hYnlGE/0.jpg</thumb>
    <type>youtube</type>
    <src>WKGK_hYnlGE</src>
  </media><media>
    <title>London City Ambience 24/7 |  ASMR Traffic Sound &amp;amp; soundscape - City Sounds &amp;amp; Car Sound Effect</title>
    <thumb>https://img.youtube.com/vi/1zxYydXWY4c/0.jpg</thumb>
    <type>youtube</type>
    <src>1zxYydXWY4c</src>
  </media><media>
    <title>🚕🗽 New York City / Walking the Streets of Manhattan</title>
    <thumb>https://img.youtube.com/vi/9bwg0-4rpRc/0.jpg</thumb>
    <type>youtube</type>
    <src>9bwg0-4rpRc</src>
  </media><media>
    <title>NYC Walking Tour | Midtown Manhattan and Upper Westside</title>
    <thumb>https://img.youtube.com/vi/h-MLf98TT-A/0.jpg</thumb>
    <type>youtube</type>
    <src>h-MLf98TT-A</src>
  </media><media>
    <title>Boston Harbor, Massachusetts - Live - Hyatt Regency Boston Harbor</title>
    <thumb>https://img.youtube.com/vi/49WtyN1V1ZQ/0.jpg</thumb>
    <type>youtube</type>
    <src>49WtyN1V1ZQ</src>
  </media><media>
    <title>Big Moose Mountain Cam 2, Maine US - Chairlift Cam</title>
    <thumb>https://img.youtube.com/vi/oE2N7RjfRPY/0.jpg</thumb>
    <type>youtube</type>
    <src>oE2N7RjfRPY</src>
  </media><media>
    <title>Cozy Cove Cabins, Jackman, Maine US - Live cam</title>
    <thumb>https://img.youtube.com/vi/Sk1vBzY2BjE/0.jpg</thumb>
    <type>youtube</type>
    <src>Sk1vBzY2BjE</src>
  </media><media>
    <title>Turners Falls, Massachusetts - Municipal Airport Live Cam</title>
    <thumb>https://img.youtube.com/vi/yu5Zg2GoRHk/0.jpg</thumb>
    <type>youtube</type>
    <src>yu5Zg2GoRHk</src>
  </media><media>
    <title>Tuscany, Italy Live Webcam - Vineyard and Restaurant</title>
    <thumb>https://img.youtube.com/vi/BIno8_T0uKc/0.jpg</thumb>
    <type>youtube</type>
    <src>BIno8_T0uKc</src>
  </media><media>
    <title>🔴 HEAVY Snow Blizzard City Walk 24/7 ❄️🌨️ Winter Storm in Helsinki Finland 4K February 2025 🔴 SLOWTV</title>
    <thumb>https://img.youtube.com/vi/LRHnJMGExGQ/0.jpg</thumb>
    <type>youtube</type>
    <src>LRHnJMGExGQ</src>
  </media><media>
    <title>🔴 HEAVY Snow Blizzard City Walk 24/7 ❄️🌨️ Winter Storm in Helsinki Finland 4K February 2025 🔴 SLOWTV</title>
    <thumb>https://img.youtube.com/vi/DfibWULw5aM/0.jpg</thumb>
    <type>youtube</type>
    <src>DfibWULw5aM</src>
  </media><media>
    <title>🔴 HEAVY Snow Blizzard City Walk 24/7 ❄️🌨️ Winter Storm in Helsinki Finland 4K February 2025 🔴 SLOWTV</title>
    <thumb>https://img.youtube.com/vi/i_F9c118HNY/0.jpg</thumb>
    <type>youtube</type>
    <src>i_F9c118HNY</src>
  </media><media>
    <title>🔴 Extreme Snow Storm in Finland ❄️ Frozen City Walk Relaxing Winter Ambience 🔴 PRE-RECORDED SLOW TV</title>
    <thumb>https://img.youtube.com/vi/3EMHtLxyaZk/0.jpg</thumb>
    <type>youtube</type>
    <src>3EMHtLxyaZk</src>
  </media><media>
    <title>🔴 Snowy Night Walk Helsinki 4K ❄️ Walk All Night Long 🌨️ 🔴 PRE-RECORDED SLOW TV CITY SOUND JAN 2025</title>
    <thumb>https://img.youtube.com/vi/JJUp5IougMw/0.jpg</thumb>
    <type>youtube</type>
    <src>JJUp5IougMw</src>
  </media><media>
    <title>Dubai Live 24/7 🇦🇪 Amazing Dubai Marina [ 4K ] Walking Tour</title>
    <thumb>https://img.youtube.com/vi/rhvTIe6bnAE/0.jpg</thumb>
    <type>youtube</type>
    <src>rhvTIe6bnAE</src>
  </media><media>
    <title>Dubai Live 24/7 🇦🇪 Deep House &amp;amp; Dubai Marina [ 4K ] Walking Tour Compilation</title>
    <thumb>https://img.youtube.com/vi/XlC19ASfeKI/0.jpg</thumb>
    <type>youtube</type>
    <src>XlC19ASfeKI</src>
  </media><media>
    <title>Dubai Live 24/7 🇦🇪 Wonderful Evening City Center [ 4K ] Walking Tour</title>
    <thumb>https://img.youtube.com/vi/y5n_d-MC3Fg/0.jpg</thumb>
    <type>youtube</type>
    <src>y5n_d-MC3Fg</src>
  </media><media>
    <title>Dubai Live 24/7 Grand Walking Tour With Lounge Music Compilation [ 4K ]</title>
    <thumb>https://img.youtube.com/vi/nV_vCvvRlmQ/0.jpg</thumb>
    <type>youtube</type>
    <src>nV_vCvvRlmQ</src>
  </media><media>
    <title>REAL CUBA TODAY STREAM: Travel to Havana Explore Cuba’s Amazing Streets and Culture - Cuba en Vivo</title>
    <thumb>https://img.youtube.com/vi/E2TtceYHpDk/0.jpg</thumb>
    <type>youtube</type>
    <src>E2TtceYHpDk</src>
  </media>
</mediaList>